cannondb/__init__.py
cannondb/btree.py
cannondb/constants.py
cannondb/database.py
cannondb/handler.py
cannondb/node.py
cannondb/serializer.py
cannondb/storages.py
cannondb/utils.py
cannondb/wrapper.py
cannondb-1.1.3.dist-info/DESCRIPTION.rst
cannondb-1.1.3.dist-info/METADATA
cannondb-1.1.3.dist-info/RECORD
cannondb-1.1.3.dist-info/WHEEL
cannondb-1.1.3.dist-info/metadata.json
cannondb-1.1.3.dist-info/top_level.txt
cannondb-1.1.3.dist-info/zip-safe
