Metadata-Version: 2.0
Name: cannondb
Version: 1.1.3
Summary: CannonDB is a lightweight but powerful key-value database created for human beings.
Home-page: https://github.com/SimonCqk/cannondb
Author: SimonCqk
Author-email: cqk0100@gmail.com
License: MIT
Requires-Dist: rwlock
